[
  {
    "dealer_id": "d1a2b3c4-5678-90ab-cdef-1234567890ab",
    "legal_name": "Aurora Ford Lincoln LLC",
    "dba_name": "Aurora Ford",
    "dealer_code": "CO-AUR-001",
    "dealer_type": "metro",
    "phone": "+1-720-555-0100",
    "website_url": "https://auroraford.com",
    "city": "Aurora",
    "state": "CO",
    "zip": "80014",
    "latitude": 39.6703,
    "longitude": -104.8194,
    "brands": ["Ford", "Lincoln"]
  },
  {
    "dealer_id": "e2b3c4d5-6789-01ab-cdef-234567890abc",
    "legal_name": "Denver Ford Sales Inc",
    "dba_name": "Denver Ford",
    "dealer_code": "CO-DEN-002",
    "dealer_type": "metro",
    "phone": "+1-303-555-0200",
    "website_url": "https://denverford.com",
    "city": "Denver",
    "state": "CO",
    "zip": "80202",
    "latitude": 39.7392,
    "longitude": -104.9903,
    "brands": ["Ford"]
  },
  {
    "dealer_id": "f3c4d5e6-7890-12ab-cdef-34567890abcd",
    "legal_name": "Palo Alto Ford Electric Vehicle Center",
    "dba_name": "Palo Alto Ford EV",
    "dealer_code": "CA-PAL-003",
    "dealer_type": "ev_focused",
    "phone": "+1-650-555-0300",
    "website_url": "https://paloaltofordev.com",
    "city": "Palo Alto",
    "state": "CA",
    "zip": "94306",
    "latitude": 37.4275,
    "longitude": -122.1697,
    "brands": ["Ford"]
  },
  {
    "dealer_id": "a4d5e6f7-8901-23ab-cdef-4567890abcde",
    "legal_name": "Chicago Lincoln Premier",
    "dba_name": "Chicago Lincoln",
    "dealer_code": "IL-CHI-004",
    "dealer_type": "metro",
    "phone": "+1-312-555-0400",
    "website_url": "https://chicagolincoln.com",
    "city": "Chicago",
    "state": "IL",
    "zip": "60601",
    "latitude": 41.8781,
    "longitude": -87.6298,
    "brands": ["Lincoln"]
  },
  {
    "dealer_id": "b5e6f7a8-9012-34ab-cdef-567890abcdef",
    "legal_name": "Texas Commercial Truck Center",
    "dba_name": "Texas Commercial Trucks",
    "dealer_code": "TX-HOU-005",
    "dealer_type": "specialty",
    "phone": "+1-713-555-0500",
    "website_url": "https://texascommercialtrucks.com",
    "city": "Houston",
    "state": "TX",
    "zip": "77002",
    "latitude": 29.7604,
    "longitude": -95.3698,
    "brands": ["Ford"]
  }
]
